negroni/__init__.py
negroni/classifiers/NEGRONILearner.py
negroni/classifiers/NEGRONIWrapper.py
negroni/classifiers/__init__.py
negroni-0.2.data/scripts/negroni
negroni-0.2.data/scripts/negroni-script
negroni-0.2.dist-info/LICENSE
negroni-0.2.dist-info/METADATA
negroni-0.2.dist-info/WHEEL
negroni-0.2.dist-info/top_level.txt
negroni-0.2.dist-info/RECORD
