Metadata-Version: 2.1
Name: negroni
Version: 0.2
Summary: eNsemblE learninG foR mOdel combiNatIon in python
Home-page: https://github.com/tommyippoz/NEGRONI
Author: Tommaso Zoppi
Author-email: tommaso.zoppi@unifi.it
Keywords: machine learning,ensemble learning,meta-learning
Classifier: Intended Audience :: Education
Classifier: Intended Audience :: Science/Research
Classifier: Intended Audience :: Developers
Classifier: Intended Audience :: Information Technology
Classifier: License :: OSI Approved :: BSD License
Classifier: Programming Language :: Python :: 2.7
Classifier: Programming Language :: Python :: 3.5
Classifier: Programming Language :: Python :: 3.6
Classifier: Programming Language :: Python :: 3.7
Classifier: Programming Language :: Python :: 3.8
Classifier: Programming Language :: Python :: 3.9
Classifier: Operating System :: OS Independent
License-File: LICENSE
